dns_checker/__init__.py
dns_checker/cli.py
dns_checker/formatters/__init__.py
dns_checker/formatters/rich_formatter.py
dns_checker/services/__init__.py
dns_checker/services/dns_service.py
dns_checker/services/http_service.py
dns_checker/services/ssl_service.py
dns_checker/utils/__init__.py
dns_checker/utils/validators.py
dns_checker_cli-0.1.1.dist-info/licenses/LICENSE
tests/__init__.py
tests/test_dns_service.py
tests/test_validators.py
dns_checker_cli-0.1.1.dist-info/METADATA
dns_checker_cli-0.1.1.dist-info/WHEEL
dns_checker_cli-0.1.1.dist-info/entry_points.txt
dns_checker_cli-0.1.1.dist-info/top_level.txt
dns_checker_cli-0.1.1.dist-info/RECORD
